examples/basic_tokenizer.py
examples/bge_m3_evaluation.py
examples/comprehensive_comparison.py
examples/custom_retriever.py
examples/embedding_models_comparison.py
examples/openai_embeddings_evaluation.py
examples/reference_based_evaluation.py
examples/retrieval_methods_comparison.py
examples/rouge_evaluation.py
ranx-k-dev/bin/activate_this.py
ranx_k/evaluation/__init__.py
ranx_k/evaluation/enhanced_rouge.py
ranx_k/evaluation/kiwi_rouge.py
ranx_k/evaluation/openai_similarity.py
ranx_k/evaluation/similarity_ranx.py
ranx_k/evaluation/utils.py
ranx_k/tokenizers/__init__.py
ranx_k/tokenizers/kiwi_tokenizer.py
ranx_k-0.0.17.dist-info/licenses/LICENSE
scripts/analyze_document_positions.py
scripts/debug_metrics.py
scripts/debug_metrics_realistic.py
scripts/debug_ranx_detailed.py
scripts/debug_recall_issue.py
scripts/debug_similarity_test.py
scripts/fix_korean_comments.py
scripts/simulate_933_score.py
scripts/test_enhanced_tokenizer.py
scripts/test_reference_based_eval.py
scripts/upload_pypi.py
tests/__init__.py
tests/test_retrieval_methods_comparison.py
tests/test_tokenizers.py
ranx_k-0.0.17.dist-info/METADATA
ranx_k-0.0.17.dist-info/WHEEL
ranx_k-0.0.17.dist-info/top_level.txt
ranx_k-0.0.17.dist-info/RECORD
