Metadata-Version: 2.4
Name: ranx-k
Version: 0.0.17
Summary: Korean-optimized RAG evaluation toolkit based on ranx with Kiwi tokenizer and Korean language support
Author-email: Pandas Studio <ontofinance@gmail.com>
Maintainer-email: Pandas Studio <ontofinance@gmail.com>
License: MIT
Project-URL: Homepage, https://github.com/tsdata/rank-k
Project-URL: Repository, https://github.com/tsdata/rank-k
Project-URL: Issues, https://github.com/tsdata/rank-k/issues
Keywords: ranx,korean,nlp,evaluation,retrieval,kiwi,rouge,ir-evaluation
Classifier: Development Status :: 4 - Beta
Classifier: Intended Audience :: Developers
Classifier: Intended Audience :: Science/Research
Classifier: License :: OSI Approved :: MIT License
Classifier: Programming Language :: Python :: 3
Classifier: Programming Language :: Python :: 3.8
Classifier: Programming Language :: Python :: 3.9
Classifier: Programming Language :: Python :: 3.10
Classifier: Programming Language :: Python :: 3.11
Classifier: Topic :: Scientific/Engineering :: Artificial Intelligence
Classifier: Topic :: Text Processing :: Linguistic
Requires-Python: >=3.8
License-File: LICENSE
Requires-Dist: kiwipiepy>=0.15.0
Requires-Dist: rouge-score>=0.1.2
Requires-Dist: sentence-transformers>=2.2.0
Requires-Dist: scikit-learn>=1.0.0
Requires-Dist: numpy>=1.21.0
Requires-Dist: tqdm>=4.62.0
Requires-Dist: ranx>=0.3.0
Requires-Dist: python-dotenv>=1.0.1
Requires-Dist: twine>=6.1.0
Provides-Extra: dev
Requires-Dist: pytest>=7.0.0; extra == "dev"
Requires-Dist: pytest-cov>=4.0.0; extra == "dev"
Requires-Dist: black>=22.0.0; extra == "dev"
Requires-Dist: isort>=5.0.0; extra == "dev"
Requires-Dist: flake8>=5.0.0; extra == "dev"
Requires-Dist: mypy>=1.0.0; extra == "dev"
Provides-Extra: docs
Requires-Dist: sphinx>=5.0.0; extra == "docs"
Requires-Dist: sphinx-rtd-theme>=1.0.0; extra == "docs"
Requires-Dist: myst-parser>=0.18.0; extra == "docs"
Dynamic: license-file
